dg/__init__.py
dg/dg.py
dg/commands/__init__.py
dg/commands/adm/__init__.py
dg/commands/adm/download_dependencies.py
dg/commands/adm/get-shell-completion-script-location.py
dg/commands/adm/store_credentials.py
dg/commands/adm/update_dev.py
dg/commands/adm/config/__init__.py
dg/commands/adm/config/set.py
dg/commands/cluster/__init__.py
dg/commands/cluster/current.py
dg/commands/cluster/edit.py
dg/commands/cluster/get_cluster_access_token.py
dg/commands/cluster/install_nfs_storage_class.py
dg/commands/cluster/login.py
dg/commands/cluster/ls.py
dg/commands/cluster/rm.py
dg/commands/cluster/use.py
dg/commands/cluster/pull_secret/__init__.py
dg/commands/cluster/pull_secret/ls.py
dg/commands/cluster/pull_secret/rm.py
dg/commands/cluster/pull_secret/set.py
dg/commands/cpd3/__init__.py
dg/commands/cpd3/install_assembly.py
dg/commands/cpd3/install_cloud_pak_for_data.py
dg/commands/cpd3/install_db2.py
dg/commands/cpd3/install_db2_data_gate.py
dg/commands/cpd3/install_db2_data_gate_stack.py
dg/commands/cpd4/__init__.py
dg/commands/cpd4/install.py
dg/commands/cpd4/install_foundational_services.py
dg/commands/cpd4/uninstall.py
dg/commands/cpd4/uninstall_foundational_services.py
dg/commands/cpd4/service/__init__.py
dg/commands/cpd4/service/install.py
dg/commands/cpd4/service/install_db2_data_gate_stack.py
dg/commands/cpd4/service/ls.py
dg/commands/fyre/__init__.py
dg/commands/fyre/login.py
dg/commands/fyre/logout.py
dg/commands/fyre/cluster/__init__.py
dg/commands/fyre/cluster/accept_transfer.py
dg/commands/fyre/cluster/add.py
dg/commands/fyre/cluster/add_worker_node.py
dg/commands/fyre/cluster/boot.py
dg/commands/fyre/cluster/boot_node.py
dg/commands/fyre/cluster/copy_ssh_key.py
dg/commands/fyre/cluster/create.py
dg/commands/fyre/cluster/create_default.py
dg/commands/fyre/cluster/create_for_db2_data_gate.py
dg/commands/fyre/cluster/details.py
dg/commands/fyre/cluster/disable_delete.py
dg/commands/fyre/cluster/edit_inf_node.py
dg/commands/fyre/cluster/edit_master_node.py
data_gate_cli-0.3.0.dist-info/LICENSE
data_gate_cli-0.3.0.dist-info/METADATA
data_gate_cli-0.3.0.dist-info/WHEEL
data_gate_cli-0.3.0.dist-info/entry_points.txt
data_gate_cli-0.3.0.dist-info/top_level.txt
data_gate_cli-0.3.0.dist-info/RECORD
