Metadata-Version: 2.1
Name: data-gate-cli
Version: 0.3.0
Summary: Db2 Data Gate CLI
Home-page: https://github.com/IBM/data-gate-cli
Author: IBM Db2 for z/OS Data Gate
Author-email: db2datagate@ibm.com
License: UNKNOWN
Download-URL: https://github.com/IBM/data-gate-cli
Platform: UNKNOWN
Classifier: Development Status :: 4 - Beta
Classifier: License :: OSI Approved :: Apache Software License
Classifier: Operating System :: MacOS
Classifier: Operating System :: Microsoft :: Windows
Classifier: Operating System :: POSIX :: Linux
Classifier: Programming Language :: Python :: 3.8
Requires-Python: >=3.8
License-File: LICENSE
Requires-Dist: asyncssh
Requires-Dist: click
Requires-Dist: click-option-group
Requires-Dist: colorama
Requires-Dist: halo
Requires-Dist: jmespath
Requires-Dist: jsonschema
Requires-Dist: kubernetes (>=12)
Requires-Dist: netifaces
Requires-Dist: pyyaml
Requires-Dist: requests
Requires-Dist: semver
Requires-Dist: tabulate
Requires-Dist: tqdm
Requires-Dist: urllib3
